django_tree_materialized/__init__.py
django_tree_materialized/admin.py
django_tree_materialized/apps.py
django_tree_materialized/exceptions.py
django_tree_materialized/models.py
django_tree_materialized/tests.py
django_tree_materialized/views.py
tests/__init__.py
tests/admin.py
tests/asgi.py
tests/models.py
tests/settings.py
tests/test_base.py
tests/urls.py
tests/wsgi.py
django_tree_materialized-0.0.6.dist-info/LICENSE
django_tree_materialized-0.0.6.dist-info/METADATA
django_tree_materialized-0.0.6.dist-info/WHEEL
django_tree_materialized-0.0.6.dist-info/top_level.txt
django_tree_materialized-0.0.6.dist-info/RECORD
