Metadata-Version: 2.1
Name: django-tree-materialized
Version: 0.0.6
Summary: Materialized tree for Django 3.x
Home-page: https://github.com/kostya-ten/django_tree_materialized/
Author: Kostya Ten
Author-email: kostya@yandex.ru
License: Apache License 2.0
Project-URL: Documentation, https://github.com/kostya-ten/django_tree_materialized/
Project-URL: Source, https://github.com/kostya-ten/django_tree_materialized/
Project-URL: Tracker, https://github.com/kostya-ten/django_tree_materialized/issues/
Project-URL: Funding, https://www.paypal.me/kostyaten/
Platform: UNKNOWN
Classifier: Environment :: Web Environment
Classifier: Natural Language :: English
Classifier: Natural Language :: Russian
Classifier: Framework :: Django
Classifier: Framework :: Django :: 3.0
Classifier: Intended Audience :: Developers
Classifier: Operating System :: OS Independent
Classifier: Programming Language :: Python
Classifier: Programming Language :: Python :: 3.6
Classifier: Programming Language :: Python :: 3.7
Classifier: Programming Language :: Python :: 3.8
Classifier: Programming Language :: Python :: 3.9
Classifier: Programming Language :: SQL
Classifier: License :: OSI Approved :: Apache Software License
Requires-Python: ~=3.6
Requires-Dist: Django (>=3.0.4)
